pycamp/__init__.py
pycamp/cli.py
pycamp_cli-1.0.1.dist-info/licenses/LICENSE
pycamp_cli-1.0.1.dist-info/METADATA
pycamp_cli-1.0.1.dist-info/WHEEL
pycamp_cli-1.0.1.dist-info/entry_points.txt
pycamp_cli-1.0.1.dist-info/top_level.txt
pycamp_cli-1.0.1.dist-info/RECORD
